sw_mc_builder/__init__.py
sw_mc_builder/__main__.py
sw_mc_builder/_handling_arguments.py
sw_mc_builder/_utils.py
sw_mc_builder/component_wrapper.py
sw_mc_builder/components.py
sw_mc_builder/handling.py
sw_mc_builder/microcontroller.py
sw_mc_builder/optimizer.py
sw_mc_builder/pseudo_components.py
sw_mc_builder/py.typed
sw_mc_builder/script_handling.py
sw_mc_builder/util.py
sw_mc_builder/wire.py
sw_mc_builder-0.1.5.dist-info/METADATA
sw_mc_builder-0.1.5.dist-info/WHEEL
sw_mc_builder-0.1.5.dist-info/entry_points.txt
sw_mc_builder-0.1.5.dist-info/top_level.txt
sw_mc_builder-0.1.5.dist-info/RECORD
