Metadata-Version: 2.4
Name: sw_mc_builder
Version: 0.1.5
Summary: Framework for building Stormworks microcontrollers
Author: Fabian Wunsch
License-Expression: MIT
Project-URL: homepage, https://github.com/stormworks-utils/sw_mc_builder
Project-URL: repository, https://github.com/stormworks-utils/sw_mc_builder
Keywords: stormworks,microcontroller,builder,automation
Classifier: Programming Language :: Python :: 3
Classifier: Development Status :: 3 - Alpha
Classifier: Operating System :: OS Independent
Classifier: Topic :: Games/Entertainment :: Simulation
Classifier: Typing :: Typed
Requires-Python: >=3.10
Requires-Dist: tumfl>=0.3.14
Requires-Dist: sw_mc_lib>=0.4.13
Provides-Extra: dev
Requires-Dist: black; extra == "dev"
Requires-Dist: isort; extra == "dev"
Requires-Dist: pip-tools; extra == "dev"
Requires-Dist: mypy; extra == "dev"
Requires-Dist: flake8; extra == "dev"
Requires-Dist: coverage; extra == "dev"
Requires-Dist: pylint; extra == "dev"
